{
	"configurations" : 
	[
		{
			"directories" : 
			[
				{
					"build" : ".",
					"jsonFile" : "directory-.-Debug-d0094a50bb2071803777.json",
					"minimumCMakeVersion" : 
					{
						"string" : "3.24"
					},
					"projectIndex" : 0,
					"source" : ".",
					"targetIndexes" : 
					[
						0
					]
				}
			],
			"name" : "Debug",
			"projects" : 
			[
				{
					"directoryIndexes" : 
					[
						0
					],
					"name" : "Parallelizing_techniques",
					"targetIndexes" : 
					[
						0
					]
				}
			],
			"targets" : 
			[
				{
					"directoryIndex" : 0,
					"id" : "Parallelizing_techniques::@6890427a1f51a3e7e1df",
					"jsonFile" : "target-Parallelizing_techniques-Debug-e89016186ec2c81ed9ca.json",
					"name" : "Parallelizing_techniques",
					"projectIndex" : 0
				}
			]
		}
	],
	"kind" : "codemodel",
	"paths" : 
	{
		"build" : "C:/Users/bloo404/Desktop/UBB/3/SEM 1/PDP/Parallelizing_techniques/cmake-build-debug",
		"source" : "C:/Users/bloo404/Desktop/UBB/3/SEM 1/PDP/Parallelizing_techniques"
	},
	"version" : 
	{
		"major" : 2,
		"minor" : 6
	}
}
